<?xml version="1.0" encoding="UTF-8"?>
<STEP-ProductInformation ContextID="Context1" WorkspaceID="Main" UseContextLocale="false">
    <Qualifiers>
        <Qualifier ID="en-US">
            <DimensionPointLink DimensionPointID="en-US"></DimensionPointLink>
        </Qualifier>
    </Qualifiers>
    <ListsOfValues>
        <ListOfValue ID="eClass_AAR686001" ParentID="eClassLOVGroup" AllowUserValueAddition="false" UseValueID="true">
            <Validation BaseType="text" MinValue="" MaxValue="" MaxLength="" InputMask=""></Validation>
            <DimensionLink DimensionID="Language"></DimensionLink>
            <ValueGroup ID="ACA216001">
                <Value QualifierID="en-US">ZTV-ING:2022-10</Value>
            </ValueGroup>
            <ValueGroup ID="ACA217001">
                <Value QualifierID="en-US">ZTV-W_LB215:2012</Value>
            </ValueGroup>
            <ValueGroup ID="ACA460001">
                <Value QualifierID="en-US">ZTV-W_LB215/A1:2019</Value>
            </ValueGroup>
        </ListOfValue>
    </ListsOfValues>
</STEP-ProductInformation>