<?xml version="1.0" encoding="UTF-8"?>
<STEP-ProductInformation ContextID="Context1" WorkspaceID="Main" UseContextLocale="false">
    <Qualifiers>
        <Qualifier ID="en-US">
            <DimensionPointLink DimensionPointID="en-US"></DimensionPointLink>
        </Qualifier>
    </Qualifiers>
    <ListsOfValues>
        <ListOfValue ID="eClass_AAB874006" ParentID="eClassLOVGroup" AllowUserValueAddition="false" UseValueID="true">
            <Validation BaseType="text" MinValue="" MaxValue="" MaxLength="" InputMask=""></Validation>
            <DimensionLink DimensionID="Language"></DimensionLink>
            <ValueGroup ID="AAA378004">
                <Value QualifierID="en-US">measuring</Value>
            </ValueGroup>
            <ValueGroup ID="AAB275004">
                <Value QualifierID="en-US">monitoring</Value>
            </ValueGroup>
            <ValueGroup ID="AAB798002">
                <Value QualifierID="en-US">Others</Value>
            </ValueGroup>
            <ValueGroup ID="AAW432002">
                <Value QualifierID="en-US">pacing</Value>
            </ValueGroup>
            <ValueGroup ID="AAW437002">
                <Value QualifierID="en-US">programming/interrogation</Value>
            </ValueGroup>
        </ListOfValue>
    </ListsOfValues>
</STEP-ProductInformation>