<?xml version="1.0" encoding="UTF-8"?>
<STEP-ProductInformation ContextID="Context1" WorkspaceID="Main" UseContextLocale="false">
    <Qualifiers>
        <Qualifier ID="en-US">
            <DimensionPointLink DimensionPointID="en-US"></DimensionPointLink>
        </Qualifier>
    </Qualifiers>
    <ListsOfValues>
        <ListOfValue ID="eClass_AAC454003" ParentID="eClassLOVGroup" AllowUserValueAddition="false" UseValueID="true">
            <Validation BaseType="text" MinValue="" MaxValue="" MaxLength="" InputMask=""></Validation>
            <DimensionLink DimensionID="Language"></DimensionLink>
            <ValueGroup ID="AAM157004">
                <Value QualifierID="en-US">Pushed-through</Value>
            </ValueGroup>
            <ValueGroup ID="AAM634001">
                <Value QualifierID="en-US">grooved hinge</Value>
            </ValueGroup>
            <ValueGroup ID="BAC231001">
                <Value QualifierID="en-US">simple</Value>
            </ValueGroup>
            <ValueGroup ID="CAA196003">
                <Value QualifierID="en-US">Riveted</Value>
            </ValueGroup>
        </ListOfValue>
    </ListsOfValues>
</STEP-ProductInformation>